{
  "schema_version": "1.0.0",
  "meta": {
    "date": "2026-06-25",
    "run_ts_utc": "2026-06-25T07:58:56Z",
    "config_hash": "1e9ad7396383",
    "vol_model": "ewma",
    "percentile_window": "3y",
    "fpr_control": "fdr",
    "calm_morning": true,
    "degraded_sources": [
      "breadth_200dma"
    ]
  },
  "composites": {
    "ofr_fsi": {
      "value": -2.724,
      "level_pct": 1.851852,
      "change_score": -0.351838,
      "color": "green",
      "staleness": {
        "asof": "2026-06-22",
        "lag_desc": "OFR 2-bd lag",
        "is_stale": false
      },
      "history": [
        {
          "date": "2026-05-12",
          "value": -2.294
        },
        {
          "date": "2026-05-13",
          "value": -2.355
        },
        {
          "date": "2026-05-14",
          "value": -2.479
        },
        {
          "date": "2026-05-15",
          "value": -2.27
        },
        {
          "date": "2026-05-18",
          "value": -2.179
        },
        {
          "date": "2026-05-19",
          "value": -2.168
        },
        {
          "date": "2026-05-20",
          "value": -2.258
        },
        {
          "date": "2026-05-21",
          "value": -2.457
        },
        {
          "date": "2026-05-22",
          "value": -2.484
        },
        {
          "date": "2026-05-25",
          "value": -2.481
        },
        {
          "date": "2026-05-26",
          "value": -2.546
        },
        {
          "date": "2026-05-27",
          "value": -2.575
        },
        {
          "date": "2026-05-28",
          "value": -2.734
        },
        {
          "date": "2026-05-29",
          "value": -2.976
        },
        {
          "date": "2026-06-01",
          "value": -2.723
        },
        {
          "date": "2026-06-02",
          "value": -2.63
        },
        {
          "date": "2026-06-03",
          "value": -2.704
        },
        {
          "date": "2026-06-04",
          "value": -2.682
        },
        {
          "date": "2026-06-05",
          "value": -2.472
        },
        {
          "date": "2026-06-08",
          "value": -2.361
        },
        {
          "date": "2026-06-09",
          "value": -2.311
        },
        {
          "date": "2026-06-10",
          "value": -1.918
        },
        {
          "date": "2026-06-11",
          "value": -1.998
        },
        {
          "date": "2026-06-12",
          "value": -2.29
        },
        {
          "date": "2026-06-15",
          "value": -2.597
        },
        {
          "date": "2026-06-16",
          "value": -2.748
        },
        {
          "date": "2026-06-17",
          "value": -2.757
        },
        {
          "date": "2026-06-18",
          "value": -2.741
        },
        {
          "date": "2026-06-19",
          "value": -2.658
        },
        {
          "date": "2026-06-22",
          "value": -2.724
        }
      ]
    },
    "nfci": {
      "value": -0.516,
      "level_pct": 16.25,
      "change_score": -0.36441,
      "color": "green",
      "staleness": {
        "asof": "2026-06-19",
        "lag_desc": "NFCI weekly",
        "is_stale": false
      },
      "history": [
        {
          "date": "2025-11-28",
          "value": -0.508
        },
        {
          "date": "2025-12-05",
          "value": -0.511
        },
        {
          "date": "2025-12-12",
          "value": -0.516
        },
        {
          "date": "2025-12-19",
          "value": -0.525
        },
        {
          "date": "2025-12-26",
          "value": -0.536
        },
        {
          "date": "2026-01-02",
          "value": -0.547
        },
        {
          "date": "2026-01-09",
          "value": -0.558
        },
        {
          "date": "2026-01-16",
          "value": -0.565
        },
        {
          "date": "2026-01-23",
          "value": -0.566
        },
        {
          "date": "2026-01-30",
          "value": -0.563
        },
        {
          "date": "2026-02-06",
          "value": -0.554
        },
        {
          "date": "2026-02-13",
          "value": -0.541
        },
        {
          "date": "2026-02-20",
          "value": -0.525
        },
        {
          "date": "2026-02-27",
          "value": -0.507
        },
        {
          "date": "2026-03-06",
          "value": -0.488
        },
        {
          "date": "2026-03-13",
          "value": -0.472
        },
        {
          "date": "2026-03-20",
          "value": -0.462
        },
        {
          "date": "2026-03-27",
          "value": -0.457
        },
        {
          "date": "2026-04-03",
          "value": -0.461
        },
        {
          "date": "2026-04-10",
          "value": -0.47
        },
        {
          "date": "2026-04-17",
          "value": -0.481
        },
        {
          "date": "2026-04-24",
          "value": -0.49
        },
        {
          "date": "2026-05-01",
          "value": -0.498
        },
        {
          "date": "2026-05-08",
          "value": -0.503
        },
        {
          "date": "2026-05-15",
          "value": -0.505
        },
        {
          "date": "2026-05-22",
          "value": -0.507
        },
        {
          "date": "2026-05-29",
          "value": -0.508
        },
        {
          "date": "2026-06-05",
          "value": -0.511
        },
        {
          "date": "2026-06-12",
          "value": -0.513
        },
        {
          "date": "2026-06-19",
          "value": -0.516
        }
      ]
    },
    "anfci": {
      "value": -0.477,
      "level_pct": 40.625,
      "change_score": -0.366061,
      "color": "green",
      "staleness": {
        "asof": "2026-06-19",
        "lag_desc": "NFCI weekly",
        "is_stale": false
      },
      "history": [
        {
          "date": "2025-11-28",
          "value": -0.535
        },
        {
          "date": "2025-12-05",
          "value": -0.528
        },
        {
          "date": "2025-12-12",
          "value": -0.522
        },
        {
          "date": "2025-12-19",
          "value": -0.523
        },
        {
          "date": "2025-12-26",
          "value": -0.531
        },
        {
          "date": "2026-01-02",
          "value": -0.54
        },
        {
          "date": "2026-01-09",
          "value": -0.549
        },
        {
          "date": "2026-01-16",
          "value": -0.553
        },
        {
          "date": "2026-01-23",
          "value": -0.551
        },
        {
          "date": "2026-01-30",
          "value": -0.542
        },
        {
          "date": "2026-02-06",
          "value": -0.529
        },
        {
          "date": "2026-02-13",
          "value": -0.514
        },
        {
          "date": "2026-02-20",
          "value": -0.495
        },
        {
          "date": "2026-02-27",
          "value": -0.473
        },
        {
          "date": "2026-03-06",
          "value": -0.447
        },
        {
          "date": "2026-03-13",
          "value": -0.424
        },
        {
          "date": "2026-03-20",
          "value": -0.41
        },
        {
          "date": "2026-03-27",
          "value": -0.406
        },
        {
          "date": "2026-04-03",
          "value": -0.416
        },
        {
          "date": "2026-04-10",
          "value": -0.434
        },
        {
          "date": "2026-04-17",
          "value": -0.452
        },
        {
          "date": "2026-04-24",
          "value": -0.463
        },
        {
          "date": "2026-05-01",
          "value": -0.466
        },
        {
          "date": "2026-05-08",
          "value": -0.462
        },
        {
          "date": "2026-05-15",
          "value": -0.458
        },
        {
          "date": "2026-05-22",
          "value": -0.456
        },
        {
          "date": "2026-05-29",
          "value": -0.46
        },
        {
          "date": "2026-06-05",
          "value": -0.467
        },
        {
          "date": "2026-06-12",
          "value": -0.473
        },
        {
          "date": "2026-06-19",
          "value": -0.477
        }
      ]
    },
    "stlfsi4": {
      "value": -0.9568,
      "level_pct": 1.875,
      "change_score": -1.319924,
      "color": "green",
      "staleness": {
        "asof": "2026-06-19",
        "lag_desc": "NFCI weekly",
        "is_stale": false
      },
      "history": [
        {
          "date": "2025-11-28",
          "value": -0.3928
        },
        {
          "date": "2025-12-05",
          "value": -0.4218
        },
        {
          "date": "2025-12-12",
          "value": -0.3553
        },
        {
          "date": "2025-12-19",
          "value": -0.3354
        },
        {
          "date": "2025-12-26",
          "value": -0.5765
        },
        {
          "date": "2026-01-02",
          "value": -0.56
        },
        {
          "date": "2026-01-09",
          "value": -0.659
        },
        {
          "date": "2026-01-16",
          "value": -0.6463
        },
        {
          "date": "2026-01-23",
          "value": -0.7078
        },
        {
          "date": "2026-01-30",
          "value": -0.6739
        },
        {
          "date": "2026-02-06",
          "value": -0.6515
        },
        {
          "date": "2026-02-13",
          "value": -0.6158
        },
        {
          "date": "2026-02-20",
          "value": -0.4841
        },
        {
          "date": "2026-02-27",
          "value": -0.4386
        },
        {
          "date": "2026-03-06",
          "value": -0.425
        },
        {
          "date": "2026-03-13",
          "value": -0.295
        },
        {
          "date": "2026-03-20",
          "value": -0.3633
        },
        {
          "date": "2026-03-27",
          "value": -0.1778
        },
        {
          "date": "2026-04-03",
          "value": -0.2361
        },
        {
          "date": "2026-04-10",
          "value": -0.6434
        },
        {
          "date": "2026-04-17",
          "value": -0.7542
        },
        {
          "date": "2026-04-24",
          "value": -0.675
        },
        {
          "date": "2026-05-01",
          "value": -0.6674
        },
        {
          "date": "2026-05-08",
          "value": -0.7596
        },
        {
          "date": "2026-05-15",
          "value": -0.7375
        },
        {
          "date": "2026-05-22",
          "value": -0.7574
        },
        {
          "date": "2026-05-29",
          "value": -0.6875
        },
        {
          "date": "2026-06-05",
          "value": -0.8671
        },
        {
          "date": "2026-06-12",
          "value": -0.769
        },
        {
          "date": "2026-06-19",
          "value": -0.9568
        }
      ]
    }
  },
  "tiles": [
    {
      "key": "ofr_fsi",
      "axis": 0,
      "label": "OFR FSI",
      "source": "ofr:fsi",
      "value": -2.724,
      "change": -0.066,
      "transform": "first_diff",
      "ewma_z": -0.351838,
      "pct_1y": 36.904762,
      "pct_3y": 38.359788,
      "level_pct_756": 1.851852,
      "robust_z": -0.324025,
      "color": "green",
      "staleness": {
        "asof": "2026-06-22",
        "lag_desc": "OFR 2-bd lag",
        "is_stale": false
      },
      "history": [
        {
          "date": "2026-05-12",
          "value": -2.294
        },
        {
          "date": "2026-05-13",
          "value": -2.355
        },
        {
          "date": "2026-05-14",
          "value": -2.479
        },
        {
          "date": "2026-05-15",
          "value": -2.27
        },
        {
          "date": "2026-05-18",
          "value": -2.179
        },
        {
          "date": "2026-05-19",
          "value": -2.168
        },
        {
          "date": "2026-05-20",
          "value": -2.258
        },
        {
          "date": "2026-05-21",
          "value": -2.457
        },
        {
          "date": "2026-05-22",
          "value": -2.484
        },
        {
          "date": "2026-05-25",
          "value": -2.481
        },
        {
          "date": "2026-05-26",
          "value": -2.546
        },
        {
          "date": "2026-05-27",
          "value": -2.575
        },
        {
          "date": "2026-05-28",
          "value": -2.734
        },
        {
          "date": "2026-05-29",
          "value": -2.976
        },
        {
          "date": "2026-06-01",
          "value": -2.723
        },
        {
          "date": "2026-06-02",
          "value": -2.63
        },
        {
          "date": "2026-06-03",
          "value": -2.704
        },
        {
          "date": "2026-06-04",
          "value": -2.682
        },
        {
          "date": "2026-06-05",
          "value": -2.472
        },
        {
          "date": "2026-06-08",
          "value": -2.361
        },
        {
          "date": "2026-06-09",
          "value": -2.311
        },
        {
          "date": "2026-06-10",
          "value": -1.918
        },
        {
          "date": "2026-06-11",
          "value": -1.998
        },
        {
          "date": "2026-06-12",
          "value": -2.29
        },
        {
          "date": "2026-06-15",
          "value": -2.597
        },
        {
          "date": "2026-06-16",
          "value": -2.748
        },
        {
          "date": "2026-06-17",
          "value": -2.757
        },
        {
          "date": "2026-06-18",
          "value": -2.741
        },
        {
          "date": "2026-06-19",
          "value": -2.658
        },
        {
          "date": "2026-06-22",
          "value": -2.724
        }
      ],
      "is_front_screen": true,
      "note": "composite anchor; daily, 2-bd lag"
    },
    {
      "key": "nfci",
      "axis": 0,
      "label": "Chicago Fed NFCI",
      "source": "fred:NFCI",
      "value": -0.516,
      "change": -0.003,
      "transform": "first_diff",
      "ewma_z": -0.36441,
      "pct_1y": 24.528302,
      "pct_3y": 24.528302,
      "level_pct_756": 16.25,
      "robust_z": 0.0,
      "color": "green",
      "staleness": {
        "asof": "2026-06-19",
        "lag_desc": "NFCI weekly",
        "is_stale": false
      },
      "history": [
        {
          "date": "2025-11-28",
          "value": -0.508
        },
        {
          "date": "2025-12-05",
          "value": -0.511
        },
        {
          "date": "2025-12-12",
          "value": -0.516
        },
        {
          "date": "2025-12-19",
          "value": -0.525
        },
        {
          "date": "2025-12-26",
          "value": -0.536
        },
        {
          "date": "2026-01-02",
          "value": -0.547
        },
        {
          "date": "2026-01-09",
          "value": -0.558
        },
        {
          "date": "2026-01-16",
          "value": -0.565
        },
        {
          "date": "2026-01-23",
          "value": -0.566
        },
        {
          "date": "2026-01-30",
          "value": -0.563
        },
        {
          "date": "2026-02-06",
          "value": -0.554
        },
        {
          "date": "2026-02-13",
          "value": -0.541
        },
        {
          "date": "2026-02-20",
          "value": -0.525
        },
        {
          "date": "2026-02-27",
          "value": -0.507
        },
        {
          "date": "2026-03-06",
          "value": -0.488
        },
        {
          "date": "2026-03-13",
          "value": -0.472
        },
        {
          "date": "2026-03-20",
          "value": -0.462
        },
        {
          "date": "2026-03-27",
          "value": -0.457
        },
        {
          "date": "2026-04-03",
          "value": -0.461
        },
        {
          "date": "2026-04-10",
          "value": -0.47
        },
        {
          "date": "2026-04-17",
          "value": -0.481
        },
        {
          "date": "2026-04-24",
          "value": -0.49
        },
        {
          "date": "2026-05-01",
          "value": -0.498
        },
        {
          "date": "2026-05-08",
          "value": -0.503
        },
        {
          "date": "2026-05-15",
          "value": -0.505
        },
        {
          "date": "2026-05-22",
          "value": -0.507
        },
        {
          "date": "2026-05-29",
          "value": -0.508
        },
        {
          "date": "2026-06-05",
          "value": -0.511
        },
        {
          "date": "2026-06-12",
          "value": -0.513
        },
        {
          "date": "2026-06-19",
          "value": -0.516
        }
      ],
      "is_front_screen": true,
      "note": "weekly composite"
    },
    {
      "key": "anfci",
      "axis": 0,
      "label": "Chicago Fed ANFCI",
      "source": "fred:ANFCI",
      "value": -0.477,
      "change": -0.004,
      "transform": "first_diff",
      "ewma_z": -0.366061,
      "pct_1y": 25.157233,
      "pct_3y": 25.157233,
      "level_pct_756": 40.625,
      "robust_z": -0.192714,
      "color": "green",
      "staleness": {
        "asof": "2026-06-19",
        "lag_desc": "NFCI weekly",
        "is_stale": false
      },
      "history": [
        {
          "date": "2025-11-28",
          "value": -0.535
        },
        {
          "date": "2025-12-05",
          "value": -0.528
        },
        {
          "date": "2025-12-12",
          "value": -0.522
        },
        {
          "date": "2025-12-19",
          "value": -0.523
        },
        {
          "date": "2025-12-26",
          "value": -0.531
        },
        {
          "date": "2026-01-02",
          "value": -0.54
        },
        {
          "date": "2026-01-09",
          "value": -0.549
        },
        {
          "date": "2026-01-16",
          "value": -0.553
        },
        {
          "date": "2026-01-23",
          "value": -0.551
        },
        {
          "date": "2026-01-30",
          "value": -0.542
        },
        {
          "date": "2026-02-06",
          "value": -0.529
        },
        {
          "date": "2026-02-13",
          "value": -0.514
        },
        {
          "date": "2026-02-20",
          "value": -0.495
        },
        {
          "date": "2026-02-27",
          "value": -0.473
        },
        {
          "date": "2026-03-06",
          "value": -0.447
        },
        {
          "date": "2026-03-13",
          "value": -0.424
        },
        {
          "date": "2026-03-20",
          "value": -0.41
        },
        {
          "date": "2026-03-27",
          "value": -0.406
        },
        {
          "date": "2026-04-03",
          "value": -0.416
        },
        {
          "date": "2026-04-10",
          "value": -0.434
        },
        {
          "date": "2026-04-17",
          "value": -0.452
        },
        {
          "date": "2026-04-24",
          "value": -0.463
        },
        {
          "date": "2026-05-01",
          "value": -0.466
        },
        {
          "date": "2026-05-08",
          "value": -0.462
        },
        {
          "date": "2026-05-15",
          "value": -0.458
        },
        {
          "date": "2026-05-22",
          "value": -0.456
        },
        {
          "date": "2026-05-29",
          "value": -0.46
        },
        {
          "date": "2026-06-05",
          "value": -0.467
        },
        {
          "date": "2026-06-12",
          "value": -0.473
        },
        {
          "date": "2026-06-19",
          "value": -0.477
        }
      ],
      "is_front_screen": false,
      "note": "adjusted NFCI; weekly composite; detect-on-composites anchor"
    },
    {
      "key": "stlfsi4",
      "axis": 0,
      "label": "St. Louis Fed FSI (STLFSI4)",
      "source": "fred:STLFSI4",
      "value": -0.9568,
      "change": -0.1878,
      "transform": "first_diff",
      "ewma_z": -1.319924,
      "pct_1y": 84.90566,
      "pct_3y": 84.90566,
      "level_pct_756": 1.875,
      "robust_z": -1.630595,
      "color": "green",
      "staleness": {
        "asof": "2026-06-19",
        "lag_desc": "NFCI weekly",
        "is_stale": false
      },
      "history": [
        {
          "date": "2025-11-28",
          "value": -0.3928
        },
        {
          "date": "2025-12-05",
          "value": -0.4218
        },
        {
          "date": "2025-12-12",
          "value": -0.3553
        },
        {
          "date": "2025-12-19",
          "value": -0.3354
        },
        {
          "date": "2025-12-26",
          "value": -0.5765
        },
        {
          "date": "2026-01-02",
          "value": -0.56
        },
        {
          "date": "2026-01-09",
          "value": -0.659
        },
        {
          "date": "2026-01-16",
          "value": -0.6463
        },
        {
          "date": "2026-01-23",
          "value": -0.7078
        },
        {
          "date": "2026-01-30",
          "value": -0.6739
        },
        {
          "date": "2026-02-06",
          "value": -0.6515
        },
        {
          "date": "2026-02-13",
          "value": -0.6158
        },
        {
          "date": "2026-02-20",
          "value": -0.4841
        },
        {
          "date": "2026-02-27",
          "value": -0.4386
        },
        {
          "date": "2026-03-06",
          "value": -0.425
        },
        {
          "date": "2026-03-13",
          "value": -0.295
        },
        {
          "date": "2026-03-20",
          "value": -0.3633
        },
        {
          "date": "2026-03-27",
          "value": -0.1778
        },
        {
          "date": "2026-04-03",
          "value": -0.2361
        },
        {
          "date": "2026-04-10",
          "value": -0.6434
        },
        {
          "date": "2026-04-17",
          "value": -0.7542
        },
        {
          "date": "2026-04-24",
          "value": -0.675
        },
        {
          "date": "2026-05-01",
          "value": -0.6674
        },
        {
          "date": "2026-05-08",
          "value": -0.7596
        },
        {
          "date": "2026-05-15",
          "value": -0.7375
        },
        {
          "date": "2026-05-22",
          "value": -0.7574
        },
        {
          "date": "2026-05-29",
          "value": -0.6875
        },
        {
          "date": "2026-06-05",
          "value": -0.8671
        },
        {
          "date": "2026-06-12",
          "value": -0.769
        },
        {
          "date": "2026-06-19",
          "value": -0.9568
        }
      ],
      "is_front_screen": false,
      "note": "weekly composite; reserved freshness window, optional anchor"
    },
    {
      "key": "spx",
      "axis": 1,
      "label": "S&P 500 / ES",
      "source": "yfinance:ES=F",
      "value": 7486.25,
      "change": 0.007778,
      "transform": "log_return",
      "ewma_z": 0.787541,
      "pct_1y": 63.888889,
      "pct_3y": 61.986755,
      "level_pct_756": 98.148148,
      "robust_z": 1.002537,
      "color": "green",
      "staleness": {
        "asof": "2026-06-25",
        "lag_desc": "EOD delayed",
        "is_stale": false
      },
      "history": [
        {
          "date": "2026-05-13",
          "value": 7469.5
        },
        {
          "date": "2026-05-14",
          "value": 7525.5
        },
        {
          "date": "2026-05-15",
          "value": 7432.25
        },
        {
          "date": "2026-05-18",
          "value": 7425.75
        },
        {
          "date": "2026-05-19",
          "value": 7378.0
        },
        {
          "date": "2026-05-20",
          "value": 7451.75
        },
        {
          "date": "2026-05-21",
          "value": 7466.0
        },
        {
          "date": "2026-05-22",
          "value": 7491.0
        },
        {
          "date": "2026-05-26",
          "value": 7537.0
        },
        {
          "date": "2026-05-27",
          "value": 7540.0
        },
        {
          "date": "2026-05-28",
          "value": 7581.75
        },
        {
          "date": "2026-05-29",
          "value": 7595.75
        },
        {
          "date": "2026-06-01",
          "value": 7613.25
        },
        {
          "date": "2026-06-02",
          "value": 7623.75
        },
        {
          "date": "2026-06-03",
          "value": 7571.75
        },
        {
          "date": "2026-06-04",
          "value": 7601.0
        },
        {
          "date": "2026-06-05",
          "value": 7400.5
        },
        {
          "date": "2026-06-08",
          "value": 7416.0
        },
        {
          "date": "2026-06-09",
          "value": 7392.75
        },
        {
          "date": "2026-06-10",
          "value": 7278.5
        },
        {
          "date": "2026-06-11",
          "value": 7396.0
        },
        {
          "date": "2026-06-12",
          "value": 7435.0
        },
        {
          "date": "2026-06-15",
          "value": 7561.25
        },
        {
          "date": "2026-06-16",
          "value": 7518.5
        },
        {
          "date": "2026-06-17",
          "value": 7424.5
        },
        {
          "date": "2026-06-18",
          "value": 7508.43017578125
        },
        {
          "date": "2026-06-22",
          "value": 7541.25
        },
        {
          "date": "2026-06-23",
          "value": 7437.5
        },
        {
          "date": "2026-06-24",
          "value": 7428.25
        },
        {
          "date": "2026-06-25",
          "value": 7486.25
        }
      ],
      "is_front_screen": true,
      "note": null
    },
    {
      "key": "vix",
      "axis": 1,
      "label": "VIX",
      "source": "yfinance:^VIX",
      "value": 17.98,
      "change": -0.65,
      "transform": "first_diff",
      "ewma_z": -0.367697,
      "pct_1y": 40.47619,
      "pct_3y": 40.770252,
      "level_pct_756": 68.832891,
      "robust_z": -0.651241,
      "color": "green",
      "staleness": {
        "asof": "2026-06-25",
        "lag_desc": "EOD delayed",
        "is_stale": false
      },
      "history": [
        {
          "date": "2026-05-14",
          "value": 17.260000228881836
        },
        {
          "date": "2026-05-15",
          "value": 18.43000030517578
        },
        {
          "date": "2026-05-18",
          "value": 17.81999969482422
        },
        {
          "date": "2026-05-19",
          "value": 18.059999465942383
        },
        {
          "date": "2026-05-20",
          "value": 17.440000534057617
        },
        {
          "date": "2026-05-21",
          "value": 16.760000228881836
        },
        {
          "date": "2026-05-22",
          "value": 16.700000762939453
        },
        {
          "date": "2026-05-25",
          "value": 16.59000015258789
        },
        {
          "date": "2026-05-26",
          "value": 17.010000228881836
        },
        {
          "date": "2026-05-27",
          "value": 16.290000915527344
        },
        {
          "date": "2026-05-28",
          "value": 15.739999771118164
        },
        {
          "date": "2026-05-29",
          "value": 15.319999694824219
        },
        {
          "date": "2026-06-01",
          "value": 16.049999237060547
        },
        {
          "date": "2026-06-02",
          "value": 15.770000457763672
        },
        {
          "date": "2026-06-03",
          "value": 16.059999465942383
        },
        {
          "date": "2026-06-04",
          "value": 15.399999618530273
        },
        {
          "date": "2026-06-05",
          "value": 21.510000228881836
        },
        {
          "date": "2026-06-08",
          "value": 18.920000076293945
        },
        {
          "date": "2026-06-09",
          "value": 19.8700008392334
        },
        {
          "date": "2026-06-10",
          "value": 22.219999313354492
        },
        {
          "date": "2026-06-11",
          "value": 19.440000534057617
        },
        {
          "date": "2026-06-12",
          "value": 17.68000030517578
        },
        {
          "date": "2026-06-15",
          "value": 16.200000762939453
        },
        {
          "date": "2026-06-16",
          "value": 16.40999984741211
        },
        {
          "date": "2026-06-17",
          "value": 18.440000534057617
        },
        {
          "date": "2026-06-18",
          "value": 16.399999618530273
        },
        {
          "date": "2026-06-22",
          "value": 17.280000686645508
        },
        {
          "date": "2026-06-23",
          "value": 19.489999771118164
        },
        {
          "date": "2026-06-24",
          "value": 18.6299991607666
        },
        {
          "date": "2026-06-25",
          "value": 17.979999542236328
        }
      ],
      "is_front_screen": true,
      "note": "prices insurance, orthogonal to SPX level"
    },
    {
      "key": "ust_2y",
      "axis": 2,
      "label": "UST 2Y",
      "source": "fred:DGS2",
      "value": 4.16,
      "change": -0.08,
      "transform": "first_diff",
      "ewma_z": -1.355985,
      "pct_1y": 84.126984,
      "pct_3y": 84.52381,
      "level_pct_756": 53.042328,
      "robust_z": -1.798667,
      "color": "green",
      "staleness": {
        "asof": "2026-06-23",
        "lag_desc": "FRED daily",
        "is_stale": false
      },
      "history": [
        {
          "date": "2026-05-11",
          "value": 3.95
        },
        {
          "date": "2026-05-12",
          "value": 4.0
        },
        {
          "date": "2026-05-13",
          "value": 3.98
        },
        {
          "date": "2026-05-14",
          "value": 4.0
        },
        {
          "date": "2026-05-15",
          "value": 4.09
        },
        {
          "date": "2026-05-18",
          "value": 4.07
        },
        {
          "date": "2026-05-19",
          "value": 4.13
        },
        {
          "date": "2026-05-20",
          "value": 4.04
        },
        {
          "date": "2026-05-21",
          "value": 4.08
        },
        {
          "date": "2026-05-22",
          "value": 4.13
        },
        {
          "date": "2026-05-26",
          "value": 4.01
        },
        {
          "date": "2026-05-27",
          "value": 4.0
        },
        {
          "date": "2026-05-28",
          "value": 3.99
        },
        {
          "date": "2026-05-29",
          "value": 3.98
        },
        {
          "date": "2026-06-01",
          "value": 4.05
        },
        {
          "date": "2026-06-02",
          "value": 4.05
        },
        {
          "date": "2026-06-03",
          "value": 4.08
        },
        {
          "date": "2026-06-04",
          "value": 4.05
        },
        {
          "date": "2026-06-05",
          "value": 4.17
        },
        {
          "date": "2026-06-08",
          "value": 4.15
        },
        {
          "date": "2026-06-09",
          "value": 4.13
        },
        {
          "date": "2026-06-10",
          "value": 4.13
        },
        {
          "date": "2026-06-11",
          "value": 4.05
        },
        {
          "date": "2026-06-12",
          "value": 4.09
        },
        {
          "date": "2026-06-15",
          "value": 4.07
        },
        {
          "date": "2026-06-16",
          "value": 4.05
        },
        {
          "date": "2026-06-17",
          "value": 4.2
        },
        {
          "date": "2026-06-18",
          "value": 4.19
        },
        {
          "date": "2026-06-22",
          "value": 4.24
        },
        {
          "date": "2026-06-23",
          "value": 4.16
        }
      ],
      "is_front_screen": true,
      "note": null
    },
    {
      "key": "real_10y",
      "axis": 3,
      "label": "10Y Real (DFII10)",
      "source": "fred:DFII10",
      "value": 2.29,
      "change": 0.01,
      "transform": "first_diff",
      "ewma_z": 0.242923,
      "pct_1y": 13.888889,
      "pct_3y": 19.444444,
      "level_pct_756": 96.825397,
      "robust_z": 0.224833,
      "color": "green",
      "staleness": {
        "asof": "2026-06-23",
        "lag_desc": "FRED daily",
        "is_stale": false
      },
      "history": [
        {
          "date": "2026-05-11",
          "value": 1.95
        },
        {
          "date": "2026-05-12",
          "value": 1.99
        },
        {
          "date": "2026-05-13",
          "value": 1.99
        },
        {
          "date": "2026-05-14",
          "value": 2.0
        },
        {
          "date": "2026-05-15",
          "value": 2.1
        },
        {
          "date": "2026-05-18",
          "value": 2.13
        },
        {
          "date": "2026-05-19",
          "value": 2.18
        },
        {
          "date": "2026-05-20",
          "value": 2.13
        },
        {
          "date": "2026-05-21",
          "value": 2.18
        },
        {
          "date": "2026-05-22",
          "value": 2.16
        },
        {
          "date": "2026-05-26",
          "value": 2.1
        },
        {
          "date": "2026-05-27",
          "value": 2.09
        },
        {
          "date": "2026-05-28",
          "value": 2.06
        },
        {
          "date": "2026-05-29",
          "value": 2.07
        },
        {
          "date": "2026-06-01",
          "value": 2.07
        },
        {
          "date": "2026-06-02",
          "value": 2.07
        },
        {
          "date": "2026-06-03",
          "value": 2.11
        },
        {
          "date": "2026-06-04",
          "value": 2.11
        },
        {
          "date": "2026-06-05",
          "value": 2.19
        },
        {
          "date": "2026-06-08",
          "value": 2.21
        },
        {
          "date": "2026-06-09",
          "value": 2.2
        },
        {
          "date": "2026-06-10",
          "value": 2.21
        },
        {
          "date": "2026-06-11",
          "value": 2.16
        },
        {
          "date": "2026-06-12",
          "value": 2.17
        },
        {
          "date": "2026-06-15",
          "value": 2.15
        },
        {
          "date": "2026-06-16",
          "value": 2.14
        },
        {
          "date": "2026-06-17",
          "value": 2.23
        },
        {
          "date": "2026-06-18",
          "value": 2.21
        },
        {
          "date": "2026-06-22",
          "value": 2.28
        },
        {
          "date": "2026-06-23",
          "value": 2.29
        }
      ],
      "is_front_screen": true,
      "note": null
    },
    {
      "key": "breakeven_10y",
      "axis": 3,
      "label": "10Y Breakeven (T10YIE)",
      "source": "fred:T10YIE",
      "value": 2.18,
      "change": -0.03,
      "transform": "first_diff",
      "ewma_z": -1.360251,
      "pct_1y": 82.539683,
      "pct_3y": 83.994709,
      "level_pct_756": 7.275132,
      "robust_z": -2.0235,
      "color": "green",
      "staleness": {
        "asof": "2026-06-24",
        "lag_desc": "FRED daily",
        "is_stale": false
      },
      "history": [
        {
          "date": "2026-05-12",
          "value": 2.47
        },
        {
          "date": "2026-05-13",
          "value": 2.47
        },
        {
          "date": "2026-05-14",
          "value": 2.47
        },
        {
          "date": "2026-05-15",
          "value": 2.49
        },
        {
          "date": "2026-05-18",
          "value": 2.48
        },
        {
          "date": "2026-05-19",
          "value": 2.49
        },
        {
          "date": "2026-05-20",
          "value": 2.44
        },
        {
          "date": "2026-05-21",
          "value": 2.39
        },
        {
          "date": "2026-05-22",
          "value": 2.4
        },
        {
          "date": "2026-05-26",
          "value": 2.4
        },
        {
          "date": "2026-05-27",
          "value": 2.39
        },
        {
          "date": "2026-05-28",
          "value": 2.39
        },
        {
          "date": "2026-05-29",
          "value": 2.38
        },
        {
          "date": "2026-06-01",
          "value": 2.4
        },
        {
          "date": "2026-06-02",
          "value": 2.39
        },
        {
          "date": "2026-06-03",
          "value": 2.38
        },
        {
          "date": "2026-06-04",
          "value": 2.36
        },
        {
          "date": "2026-06-05",
          "value": 2.36
        },
        {
          "date": "2026-06-08",
          "value": 2.35
        },
        {
          "date": "2026-06-09",
          "value": 2.33
        },
        {
          "date": "2026-06-10",
          "value": 2.34
        },
        {
          "date": "2026-06-11",
          "value": 2.29
        },
        {
          "date": "2026-06-12",
          "value": 2.31
        },
        {
          "date": "2026-06-15",
          "value": 2.32
        },
        {
          "date": "2026-06-16",
          "value": 2.29
        },
        {
          "date": "2026-06-17",
          "value": 2.26
        },
        {
          "date": "2026-06-18",
          "value": 2.25
        },
        {
          "date": "2026-06-22",
          "value": 2.23
        },
        {
          "date": "2026-06-23",
          "value": 2.21
        },
        {
          "date": "2026-06-24",
          "value": 2.18
        }
      ],
      "is_front_screen": true,
      "note": null
    },
    {
      "key": "curve_2s10s",
      "axis": 4,
      "label": "2s10s (T10Y2Y)",
      "source": "fred:T10Y2Y",
      "value": 0.3,
      "change": -0.04,
      "transform": "sign",
      "ewma_z": null,
      "pct_1y": null,
      "pct_3y": null,
      "level_pct_756": 55.291005,
      "robust_z": 0.23075,
      "color": "green",
      "staleness": {
        "asof": "2026-06-24",
        "lag_desc": "FRED daily",
        "is_stale": false
      },
      "history": [
        {
          "date": "2026-05-12",
          "value": 0.46
        },
        {
          "date": "2026-05-13",
          "value": 0.48
        },
        {
          "date": "2026-05-14",
          "value": 0.47
        },
        {
          "date": "2026-05-15",
          "value": 0.5
        },
        {
          "date": "2026-05-18",
          "value": 0.54
        },
        {
          "date": "2026-05-19",
          "value": 0.54
        },
        {
          "date": "2026-05-20",
          "value": 0.53
        },
        {
          "date": "2026-05-21",
          "value": 0.49
        },
        {
          "date": "2026-05-22",
          "value": 0.43
        },
        {
          "date": "2026-05-26",
          "value": 0.49
        },
        {
          "date": "2026-05-27",
          "value": 0.48
        },
        {
          "date": "2026-05-28",
          "value": 0.46
        },
        {
          "date": "2026-05-29",
          "value": 0.47
        },
        {
          "date": "2026-06-01",
          "value": 0.42
        },
        {
          "date": "2026-06-02",
          "value": 0.41
        },
        {
          "date": "2026-06-03",
          "value": 0.41
        },
        {
          "date": "2026-06-04",
          "value": 0.42
        },
        {
          "date": "2026-06-05",
          "value": 0.38
        },
        {
          "date": "2026-06-08",
          "value": 0.41
        },
        {
          "date": "2026-06-09",
          "value": 0.4
        },
        {
          "date": "2026-06-10",
          "value": 0.42
        },
        {
          "date": "2026-06-11",
          "value": 0.4
        },
        {
          "date": "2026-06-12",
          "value": 0.39
        },
        {
          "date": "2026-06-15",
          "value": 0.4
        },
        {
          "date": "2026-06-16",
          "value": 0.38
        },
        {
          "date": "2026-06-17",
          "value": 0.29
        },
        {
          "date": "2026-06-18",
          "value": 0.27
        },
        {
          "date": "2026-06-22",
          "value": 0.27
        },
        {
          "date": "2026-06-23",
          "value": 0.34
        },
        {
          "date": "2026-06-24",
          "value": 0.3
        }
      ],
      "is_front_screen": true,
      "note": "sign-change is the signal"
    },
    {
      "key": "hy_oas",
      "axis": 5,
      "label": "HY OAS (BAMLH0A0HYM2)",
      "source": "fred:BAMLH0A0HYM2",
      "value": 2.71,
      "change": 0.06,
      "transform": "first_diff",
      "ewma_z": 1.535454,
      "pct_1y": 88.888889,
      "pct_3y": 88.624339,
      "level_pct_756": 9.259259,
      "robust_z": 1.349,
      "color": "green",
      "staleness": {
        "asof": "2026-06-23",
        "lag_desc": "FRED daily",
        "is_stale": false
      },
      "history": [
        {
          "date": "2026-05-14",
          "value": 2.76
        },
        {
          "date": "2026-05-15",
          "value": 2.8
        },
        {
          "date": "2026-05-18",
          "value": 2.83
        },
        {
          "date": "2026-05-19",
          "value": 2.86
        },
        {
          "date": "2026-05-20",
          "value": 2.8
        },
        {
          "date": "2026-05-21",
          "value": 2.78
        },
        {
          "date": "2026-05-22",
          "value": 2.74
        },
        {
          "date": "2026-05-25",
          "value": 2.74
        },
        {
          "date": "2026-05-26",
          "value": 2.72
        },
        {
          "date": "2026-05-27",
          "value": 2.71
        },
        {
          "date": "2026-05-28",
          "value": 2.72
        },
        {
          "date": "2026-05-29",
          "value": 2.72
        },
        {
          "date": "2026-05-31",
          "value": 2.74
        },
        {
          "date": "2026-06-01",
          "value": 2.72
        },
        {
          "date": "2026-06-02",
          "value": 2.71
        },
        {
          "date": "2026-06-03",
          "value": 2.75
        },
        {
          "date": "2026-06-04",
          "value": 2.74
        },
        {
          "date": "2026-06-05",
          "value": 2.76
        },
        {
          "date": "2026-06-08",
          "value": 2.75
        },
        {
          "date": "2026-06-09",
          "value": 2.78
        },
        {
          "date": "2026-06-10",
          "value": 2.8
        },
        {
          "date": "2026-06-11",
          "value": 2.78
        },
        {
          "date": "2026-06-12",
          "value": 2.71
        },
        {
          "date": "2026-06-15",
          "value": 2.66
        },
        {
          "date": "2026-06-16",
          "value": 2.71
        },
        {
          "date": "2026-06-17",
          "value": 2.63
        },
        {
          "date": "2026-06-18",
          "value": 2.66
        },
        {
          "date": "2026-06-19",
          "value": 2.66
        },
        {
          "date": "2026-06-22",
          "value": 2.65
        },
        {
          "date": "2026-06-23",
          "value": 2.71
        }
      ],
      "is_front_screen": true,
      "note": "OAS not HYG/LQD ETF"
    },
    {
      "key": "ig_oas",
      "axis": 5,
      "label": "IG OAS (BAMLC0A0CM)",
      "source": "fred:BAMLC0A0CM",
      "value": 0.74,
      "change": 0.0,
      "transform": "first_diff",
      "ewma_z": 0.0,
      "pct_1y": 36.904762,
      "pct_3y": 38.756614,
      "level_pct_756": 4.232804,
      "robust_z": 0.0,
      "color": "green",
      "staleness": {
        "asof": "2026-06-23",
        "lag_desc": "FRED daily",
        "is_stale": false
      },
      "history": [
        {
          "date": "2026-05-14",
          "value": 0.76
        },
        {
          "date": "2026-05-15",
          "value": 0.75
        },
        {
          "date": "2026-05-18",
          "value": 0.75
        },
        {
          "date": "2026-05-19",
          "value": 0.76
        },
        {
          "date": "2026-05-20",
          "value": 0.75
        },
        {
          "date": "2026-05-21",
          "value": 0.75
        },
        {
          "date": "2026-05-22",
          "value": 0.74
        },
        {
          "date": "2026-05-25",
          "value": 0.74
        },
        {
          "date": "2026-05-26",
          "value": 0.74
        },
        {
          "date": "2026-05-27",
          "value": 0.74
        },
        {
          "date": "2026-05-28",
          "value": 0.73
        },
        {
          "date": "2026-05-29",
          "value": 0.73
        },
        {
          "date": "2026-05-31",
          "value": 0.74
        },
        {
          "date": "2026-06-01",
          "value": 0.73
        },
        {
          "date": "2026-06-02",
          "value": 0.74
        },
        {
          "date": "2026-06-03",
          "value": 0.74
        },
        {
          "date": "2026-06-04",
          "value": 0.74
        },
        {
          "date": "2026-06-05",
          "value": 0.74
        },
        {
          "date": "2026-06-08",
          "value": 0.75
        },
        {
          "date": "2026-06-09",
          "value": 0.75
        },
        {
          "date": "2026-06-10",
          "value": 0.75
        },
        {
          "date": "2026-06-11",
          "value": 0.75
        },
        {
          "date": "2026-06-12",
          "value": 0.74
        },
        {
          "date": "2026-06-15",
          "value": 0.73
        },
        {
          "date": "2026-06-16",
          "value": 0.75
        },
        {
          "date": "2026-06-17",
          "value": 0.74
        },
        {
          "date": "2026-06-18",
          "value": 0.74
        },
        {
          "date": "2026-06-19",
          "value": 0.74
        },
        {
          "date": "2026-06-22",
          "value": 0.74
        },
        {
          "date": "2026-06-23",
          "value": 0.74
        }
      ],
      "is_front_screen": false,
      "note": null
    },
    {
      "key": "usd_broad",
      "axis": 6,
      "label": "Fed Broad USD (DTWEXBGS)",
      "source": "fred:DTWEXBGS",
      "value": 120.3958,
      "change": 0.008413,
      "transform": "log_return",
      "ewma_z": 3.366625,
      "pct_1y": 99.603175,
      "pct_3y": 99.074074,
      "level_pct_756": 34.52381,
      "robust_z": 3.3627,
      "color": "red",
      "staleness": {
        "asof": "2026-06-18",
        "lag_desc": "Fed H.10 broad $ (multi-day lag)",
        "is_stale": false
      },
      "history": [
        {
          "date": "2026-05-07",
          "value": 118.0116
        },
        {
          "date": "2026-05-08",
          "value": 118.0392
        },
        {
          "date": "2026-05-11",
          "value": 118.0562
        },
        {
          "date": "2026-05-12",
          "value": 118.5238
        },
        {
          "date": "2026-05-13",
          "value": 118.4737
        },
        {
          "date": "2026-05-14",
          "value": 118.6696
        },
        {
          "date": "2026-05-15",
          "value": 119.2825
        },
        {
          "date": "2026-05-18",
          "value": 119.0574
        },
        {
          "date": "2026-05-19",
          "value": 119.451
        },
        {
          "date": "2026-05-20",
          "value": 119.1624
        },
        {
          "date": "2026-05-21",
          "value": 119.369
        },
        {
          "date": "2026-05-22",
          "value": 119.2868
        },
        {
          "date": "2026-05-26",
          "value": 119.1696
        },
        {
          "date": "2026-05-27",
          "value": 119.1829
        },
        {
          "date": "2026-05-28",
          "value": 119.0318
        },
        {
          "date": "2026-05-29",
          "value": 118.8783
        },
        {
          "date": "2026-06-01",
          "value": 119.1653
        },
        {
          "date": "2026-06-02",
          "value": 119.0359
        },
        {
          "date": "2026-06-03",
          "value": 119.3848
        },
        {
          "date": "2026-06-04",
          "value": 119.3615
        },
        {
          "date": "2026-06-05",
          "value": 120.0831
        },
        {
          "date": "2026-06-08",
          "value": 120.034
        },
        {
          "date": "2026-06-09",
          "value": 119.9617
        },
        {
          "date": "2026-06-10",
          "value": 119.9134
        },
        {
          "date": "2026-06-11",
          "value": 120.1174
        },
        {
          "date": "2026-06-12",
          "value": 119.5073
        },
        {
          "date": "2026-06-15",
          "value": 119.3158
        },
        {
          "date": "2026-06-16",
          "value": 119.256
        },
        {
          "date": "2026-06-17",
          "value": 119.3871
        },
        {
          "date": "2026-06-18",
          "value": 120.3958
        }
      ],
      "is_front_screen": true,
      "note": "Broad = economic gauge; DXY is EUR-story proxy"
    },
    {
      "key": "usdjpy",
      "axis": 6,
      "label": "USDJPY",
      "source": "yfinance:JPY=X",
      "value": 161.811005,
      "change": 0.001311,
      "transform": "log_return",
      "ewma_z": 0.514485,
      "pct_1y": 47.222222,
      "pct_3y": 45.899471,
      "level_pct_756": 100.0,
      "robust_z": 0.163337,
      "color": "green",
      "staleness": {
        "asof": "2026-06-25",
        "lag_desc": "EOD delayed",
        "is_stale": false
      },
      "history": [
        {
          "date": "2026-05-15",
          "value": 158.3820037841797
        },
        {
          "date": "2026-05-18",
          "value": 158.843994140625
        },
        {
          "date": "2026-05-19",
          "value": 158.86099243164062
        },
        {
          "date": "2026-05-20",
          "value": 159.03500366210938
        },
        {
          "date": "2026-05-21",
          "value": 158.88800048828125
        },
        {
          "date": "2026-05-22",
          "value": 159.01800537109375
        },
        {
          "date": "2026-05-25",
          "value": 158.9459991455078
        },
        {
          "date": "2026-05-26",
          "value": 158.95399475097656
        },
        {
          "date": "2026-05-27",
          "value": 159.2429962158203
        },
        {
          "date": "2026-05-28",
          "value": 159.5679931640625
        },
        {
          "date": "2026-05-29",
          "value": 159.27000427246094
        },
        {
          "date": "2026-06-01",
          "value": 159.35299682617188
        },
        {
          "date": "2026-06-02",
          "value": 159.63600158691406
        },
        {
          "date": "2026-06-03",
          "value": 159.96800231933594
        },
        {
          "date": "2026-06-04",
          "value": 159.94000244140625
        },
        {
          "date": "2026-06-05",
          "value": 159.99000549316406
        },
        {
          "date": "2026-06-08",
          "value": 160.32699584960938
        },
        {
          "date": "2026-06-09",
          "value": 160.1739959716797
        },
        {
          "date": "2026-06-10",
          "value": 160.38400268554688
        },
        {
          "date": "2026-06-11",
          "value": 160.52699279785156
        },
        {
          "date": "2026-06-12",
          "value": 160.1300048828125
        },
        {
          "date": "2026-06-15",
          "value": 159.9550018310547
        },
        {
          "date": "2026-06-16",
          "value": 160.22900390625
        },
        {
          "date": "2026-06-17",
          "value": 160.41900634765625
        },
        {
          "date": "2026-06-18",
          "value": 160.60000610351562
        },
        {
          "date": "2026-06-19",
          "value": 161.28900146484375
        },
        {
          "date": "2026-06-22",
          "value": 161.43299865722656
        },
        {
          "date": "2026-06-23",
          "value": 161.57000732421875
        },
        {
          "date": "2026-06-24",
          "value": 161.5989990234375
        },
        {
          "date": "2026-06-25",
          "value": 161.81100463867188
        }
      ],
      "is_front_screen": true,
      "note": null
    },
    {
      "key": "brent",
      "axis": 7,
      "label": "Brent",
      "source": "yfinance:BZ=F",
      "value": 73.220001,
      "change": -0.007077,
      "transform": "log_return",
      "ewma_z": -0.209549,
      "pct_1y": 19.84127,
      "pct_3y": 18.013245,
      "level_pct_756": 37.301587,
      "robust_z": -0.445024,
      "color": "green",
      "staleness": {
        "asof": "2026-06-25",
        "lag_desc": "EOD delayed",
        "is_stale": false
      },
      "history": [
        {
          "date": "2026-05-13",
          "value": 105.62999725341797
        },
        {
          "date": "2026-05-14",
          "value": 105.72000122070312
        },
        {
          "date": "2026-05-15",
          "value": 109.26000213623047
        },
        {
          "date": "2026-05-18",
          "value": 112.0999984741211
        },
        {
          "date": "2026-05-19",
          "value": 111.27999877929688
        },
        {
          "date": "2026-05-20",
          "value": 105.0199966430664
        },
        {
          "date": "2026-05-21",
          "value": 102.58000183105469
        },
        {
          "date": "2026-05-22",
          "value": 103.54000091552734
        },
        {
          "date": "2026-05-26",
          "value": 99.58000183105469
        },
        {
          "date": "2026-05-27",
          "value": 94.29000091552734
        },
        {
          "date": "2026-05-28",
          "value": 93.70999908447266
        },
        {
          "date": "2026-05-29",
          "value": 92.05000305175781
        },
        {
          "date": "2026-06-01",
          "value": 94.9800033569336
        },
        {
          "date": "2026-06-02",
          "value": 96.0
        },
        {
          "date": "2026-06-03",
          "value": 97.80999755859375
        },
        {
          "date": "2026-06-04",
          "value": 95.02999877929688
        },
        {
          "date": "2026-06-05",
          "value": 93.08999633789062
        },
        {
          "date": "2026-06-08",
          "value": 94.25
        },
        {
          "date": "2026-06-09",
          "value": 91.44999694824219
        },
        {
          "date": "2026-06-10",
          "value": 93.0999984741211
        },
        {
          "date": "2026-06-11",
          "value": 90.37999725341797
        },
        {
          "date": "2026-06-12",
          "value": 87.33000183105469
        },
        {
          "date": "2026-06-15",
          "value": 83.16999816894531
        },
        {
          "date": "2026-06-16",
          "value": 78.95999908447266
        },
        {
          "date": "2026-06-17",
          "value": 79.55000305175781
        },
        {
          "date": "2026-06-18",
          "value": 79.8499984741211
        },
        {
          "date": "2026-06-22",
          "value": 77.9000015258789
        },
        {
          "date": "2026-06-23",
          "value": 77.08000183105469
        },
        {
          "date": "2026-06-24",
          "value": 73.73999786376953
        },
        {
          "date": "2026-06-25",
          "value": 73.22000122070312
        }
      ],
      "is_front_screen": false,
      "note": null
    },
    {
      "key": "copper_gold",
      "axis": 7,
      "label": "Copper / Gold ratio",
      "source": "derived:ratio:yfinance:HG=F/yfinance:GC=F",
      "value": 0.001517,
      "change": 2.8e-05,
      "transform": "ratio",
      "ewma_z": 1.323063,
      "pct_1y": 84.52381,
      "pct_3y": 81.962865,
      "level_pct_756": 38.013245,
      "robust_z": 1.405852,
      "color": "green",
      "staleness": {
        "asof": "2026-06-25",
        "lag_desc": "EOD delayed",
        "is_stale": false
      },
      "history": [
        {
          "date": "2026-05-13",
          "value": 0.0014124996654415547
        },
        {
          "date": "2026-05-14",
          "value": 0.0014038819130294511
        },
        {
          "date": "2026-05-15",
          "value": 0.0013722069444902928
        },
        {
          "date": "2026-05-18",
          "value": 0.0013777045219040126
        },
        {
          "date": "2026-05-19",
          "value": 0.0013680847322763857
        },
        {
          "date": "2026-05-20",
          "value": 0.0013882330534661688
        },
        {
          "date": "2026-05-21",
          "value": 0.0013782546012319427
        },
        {
          "date": "2026-05-22",
          "value": 0.0014027869957154158
        },
        {
          "date": "2026-05-26",
          "value": 0.0014134299615735104
        },
        {
          "date": "2026-05-27",
          "value": 0.0014176503267765313
        },
        {
          "date": "2026-05-28",
          "value": 0.0014215545053885338
        },
        {
          "date": "2026-05-29",
          "value": 0.001394474275043405
        },
        {
          "date": "2026-06-01",
          "value": 0.0014578119152479866
        },
        {
          "date": "2026-06-02",
          "value": 0.0014812545384452814
        },
        {
          "date": "2026-06-03",
          "value": 0.0014607703160654396
        },
        {
          "date": "2026-06-04",
          "value": 0.001454712105216061
        },
        {
          "date": "2026-06-05",
          "value": 0.001444167778605759
        },
        {
          "date": "2026-06-08",
          "value": 0.0014597892804081747
        },
        {
          "date": "2026-06-09",
          "value": 0.001479460040168583
        },
        {
          "date": "2026-06-10",
          "value": 0.001521104078523102
        },
        {
          "date": "2026-06-11",
          "value": 0.0015302055472231518
        },
        {
          "date": "2026-06-12",
          "value": 0.0015256227830409439
        },
        {
          "date": "2026-06-15",
          "value": 0.001497805008385847
        },
        {
          "date": "2026-06-16",
          "value": 0.001498302890834712
        },
        {
          "date": "2026-06-17",
          "value": 0.0014869577861350144
        },
        {
          "date": "2026-06-18",
          "value": 0.001509078774283296
        },
        {
          "date": "2026-06-22",
          "value": 0.0015200029405798754
        },
        {
          "date": "2026-06-23",
          "value": 0.0014869609286465473
        },
        {
          "date": "2026-06-24",
          "value": 0.0014893616437510909
        },
        {
          "date": "2026-06-25",
          "value": 0.0015173226554756696
        }
      ],
      "is_front_screen": false,
      "note": "clean growth read (daily copper/gold ratio supersedes monthly-copper); oil is geopolitics-contaminated"
    },
    {
      "key": "vix_term",
      "axis": 8,
      "label": "VIX / VIX3M",
      "source": "derived:ratio:yfinance:^VIX/yfinance:^VIX3M",
      "value": 0.838017,
      "change": -0.05626,
      "transform": "ratio",
      "ewma_z": -1.179477,
      "pct_1y": 78.968254,
      "pct_3y": 79.010695,
      "level_pct_756": 16.82243,
      "robust_z": -2.486163,
      "color": "green",
      "staleness": {
        "asof": "2026-06-18",
        "lag_desc": "EOD delayed",
        "is_stale": false
      },
      "history": [
        {
          "date": "2026-05-07",
          "value": 0.8393120198296771
        },
        {
          "date": "2026-05-08",
          "value": 0.8385366114174447
        },
        {
          "date": "2026-05-11",
          "value": 0.8653483690597517
        },
        {
          "date": "2026-05-12",
          "value": 0.8550379747294448
        },
        {
          "date": "2026-05-13",
          "value": 0.8437205184962384
        },
        {
          "date": "2026-05-14",
          "value": 0.8278177416352244
        },
        {
          "date": "2026-05-15",
          "value": 0.8628277049881808
        },
        {
          "date": "2026-05-18",
          "value": 0.851816425900372
        },
        {
          "date": "2026-05-19",
          "value": 0.8551135770976567
        },
        {
          "date": "2026-05-20",
          "value": 0.8400770877542982
        },
        {
          "date": "2026-05-21",
          "value": 0.8380000114440918
        },
        {
          "date": "2026-05-22",
          "value": 0.8337493854442927
        },
        {
          "date": "2026-05-26",
          "value": 0.8552036576599661
        },
        {
          "date": "2026-05-27",
          "value": 0.8375321478941401
        },
        {
          "date": "2026-05-28",
          "value": 0.8236524996546611
        },
        {
          "date": "2026-05-29",
          "value": 0.8210074930385863
        },
        {
          "date": "2026-06-01",
          "value": 0.8260421505389856
        },
        {
          "date": "2026-06-02",
          "value": 0.8091329216500514
        },
        {
          "date": "2026-06-03",
          "value": 0.8127529999958494
        },
        {
          "date": "2026-06-04",
          "value": 0.8008320325076488
        },
        {
          "date": "2026-06-05",
          "value": 0.9857928748726832
        },
        {
          "date": "2026-06-08",
          "value": 0.9100528736467367
        },
        {
          "date": "2026-06-09",
          "value": 0.9324261537870806
        },
        {
          "date": "2026-06-10",
          "value": 0.9707295721206117
        },
        {
          "date": "2026-06-11",
          "value": 0.9075630469101799
        },
        {
          "date": "2026-06-12",
          "value": 0.8620185328071865
        },
        {
          "date": "2026-06-15",
          "value": 0.8367768725315796
        },
        {
          "date": "2026-06-16",
          "value": 0.8402457383748667
        },
        {
          "date": "2026-06-17",
          "value": 0.894277390084877
        },
        {
          "date": "2026-06-18",
          "value": 0.8380173671064322
        }
      ],
      "is_front_screen": true,
      "note": "ratio>1.0 = backwardation = acute stress"
    },
    {
      "key": "move_proxy",
      "axis": 9,
      "label": "Rates vol (MOVE proxy)",
      "source": "derived:realized_vol_dgs10_20d",
      "value": 0.041243,
      "change": -0.0,
      "transform": "level",
      "ewma_z": null,
      "pct_1y": null,
      "pct_3y": null,
      "level_pct_756": 22.520107,
      "robust_z": -0.602978,
      "color": "green",
      "staleness": {
        "asof": "2026-06-23",
        "lag_desc": "FRED daily",
        "is_stale": false
      },
      "history": [
        {
          "date": "2026-05-11",
          "value": 0.03878143885933068
        },
        {
          "date": "2026-05-12",
          "value": 0.03794733192202059
        },
        {
          "date": "2026-05-13",
          "value": 0.03771935842508463
        },
        {
          "date": "2026-05-14",
          "value": 0.037399866309921516
        },
        {
          "date": "2026-05-15",
          "value": 0.04150602365922325
        },
        {
          "date": "2026-05-18",
          "value": 0.04133702940463913
        },
        {
          "date": "2026-05-19",
          "value": 0.04210403781111734
        },
        {
          "date": "2026-05-20",
          "value": 0.0493229155667018
        },
        {
          "date": "2026-05-21",
          "value": 0.04901785389018979
        },
        {
          "date": "2026-05-22",
          "value": 0.04836062447901179
        },
        {
          "date": "2026-05-26",
          "value": 0.05038600996308392
        },
        {
          "date": "2026-05-27",
          "value": 0.0507346035758632
        },
        {
          "date": "2026-05-28",
          "value": 0.04972675336275227
        },
        {
          "date": "2026-05-29",
          "value": 0.049484846165265536
        },
        {
          "date": "2026-06-01",
          "value": 0.04953786430600328
        },
        {
          "date": "2026-06-02",
          "value": 0.04790354892907195
        },
        {
          "date": "2026-06-03",
          "value": 0.04807286136688755
        },
        {
          "date": "2026-06-04",
          "value": 0.04543952024394619
        },
        {
          "date": "2026-06-05",
          "value": 0.04733920151417847
        },
        {
          "date": "2026-06-08",
          "value": 0.04657252408878003
        },
        {
          "date": "2026-06-09",
          "value": 0.04674130935264857
        },
        {
          "date": "2026-06-10",
          "value": 0.04620335485654686
        },
        {
          "date": "2026-06-11",
          "value": 0.051524266127718786
        },
        {
          "date": "2026-06-12",
          "value": 0.05191098149717446
        },
        {
          "date": "2026-06-15",
          "value": 0.04409081537009708
        },
        {
          "date": "2026-06-16",
          "value": 0.04426059195266131
        },
        {
          "date": "2026-06-17",
          "value": 0.04426059195266139
        },
        {
          "date": "2026-06-18",
          "value": 0.03943031828428472
        },
        {
          "date": "2026-06-22",
          "value": 0.04124318125460252
        },
        {
          "date": "2026-06-23",
          "value": 0.041243181254602516
        }
      ],
      "is_front_screen": false,
      "note": "free proxy = 20d realized vol of DGS10 changes; ^MOVE delayed if licensed"
    },
    {
      "key": "breadth_200dma",
      "axis": 10,
      "label": "% S&P >200DMA",
      "source": "vendor:SPXA200R",
      "value": null,
      "change": null,
      "transform": "first_diff",
      "ewma_z": null,
      "pct_1y": null,
      "pct_3y": null,
      "level_pct_756": null,
      "robust_z": null,
      "color": "gray",
      "staleness": {
        "asof": null,
        "lag_desc": "EOD vendor",
        "is_stale": true
      },
      "history": [],
      "is_front_screen": true,
      "note": "KNOWN-UNAVAILABLE: no clean free %>200DMA feed (StockCharts $SPXA200R gated); BREADTH axis covered by rsp_spy"
    },
    {
      "key": "rsp_spy",
      "axis": 10,
      "label": "RSP/SPY (equal vs cap weight)",
      "source": "derived:ratio:yfinance:RSP/yfinance:SPY",
      "value": 0.286918,
      "change": 0.002164,
      "transform": "ratio",
      "ewma_z": 1.366673,
      "pct_1y": 82.539683,
      "pct_3y": 82.023968,
      "level_pct_756": 18.085106,
      "robust_z": 1.70213,
      "color": "green",
      "staleness": {
        "asof": "2026-06-24",
        "lag_desc": "EOD delayed",
        "is_stale": false
      },
      "history": [
        {
          "date": "2026-05-12",
          "value": 0.27609797011676784
        },
        {
          "date": "2026-05-13",
          "value": 0.2733628791695318
        },
        {
          "date": "2026-05-14",
          "value": 0.27221087228056545
        },
        {
          "date": "2026-05-15",
          "value": 0.27268422990479135
        },
        {
          "date": "2026-05-18",
          "value": 0.27455492635044565
        },
        {
          "date": "2026-05-19",
          "value": 0.2747877291157992
        },
        {
          "date": "2026-05-20",
          "value": 0.27498145272317664
        },
        {
          "date": "2026-05-21",
          "value": 0.27562205782627663
        },
        {
          "date": "2026-05-22",
          "value": 0.2770505844277353
        },
        {
          "date": "2026-05-26",
          "value": 0.2766357025279673
        },
        {
          "date": "2026-05-27",
          "value": 0.2764837558538517
        },
        {
          "date": "2026-05-28",
          "value": 0.27597403490279265
        },
        {
          "date": "2026-05-29",
          "value": 0.2760548953346445
        },
        {
          "date": "2026-06-01",
          "value": 0.275806170767608
        },
        {
          "date": "2026-06-02",
          "value": 0.27652486441118557
        },
        {
          "date": "2026-06-03",
          "value": 0.2774315903549174
        },
        {
          "date": "2026-06-04",
          "value": 0.2784741501703904
        },
        {
          "date": "2026-06-05",
          "value": 0.2817842929575003
        },
        {
          "date": "2026-06-08",
          "value": 0.28085009718132864
        },
        {
          "date": "2026-06-09",
          "value": 0.28382064433351023
        },
        {
          "date": "2026-06-10",
          "value": 0.2847001100926385
        },
        {
          "date": "2026-06-11",
          "value": 0.28430654579208536
        },
        {
          "date": "2026-06-12",
          "value": 0.28533871775730957
        },
        {
          "date": "2026-06-15",
          "value": 0.28202376702445636
        },
        {
          "date": "2026-06-16",
          "value": 0.282768906129928
        },
        {
          "date": "2026-06-17",
          "value": 0.28205301135784683
        },
        {
          "date": "2026-06-18",
          "value": 0.28116882644515695
        },
        {
          "date": "2026-06-22",
          "value": 0.28158626054293157
        },
        {
          "date": "2026-06-23",
          "value": 0.2847542115696222
        },
        {
          "date": "2026-06-24",
          "value": 0.28691834554136364
        }
      ],
      "is_front_screen": true,
      "note": null
    },
    {
      "key": "net_liquidity",
      "axis": 11,
      "label": "Net Liquidity (WALCL-TGA-RRP)",
      "source": "derived:fred_walcl_wtregen_rrpontsyd",
      "value": 5855704.172,
      "change": -41570.441,
      "transform": "first_diff",
      "ewma_z": -0.565145,
      "pct_1y": 51.923077,
      "pct_3y": 51.923077,
      "level_pct_756": 21.656051,
      "robust_z": -0.616266,
      "color": "green",
      "staleness": {
        "asof": "2026-06-17",
        "lag_desc": "H.4.1 weekly Thu",
        "is_stale": false
      },
      "history": [
        {
          "date": "2025-11-26",
          "value": 5649022.783
        },
        {
          "date": "2025-12-03",
          "value": 5598611.486
        },
        {
          "date": "2025-12-10",
          "value": 5680351.955
        },
        {
          "date": "2025-12-17",
          "value": 5723757.639
        },
        {
          "date": "2025-12-24",
          "value": 5744106.197
        },
        {
          "date": "2025-12-31",
          "value": 5803206.007
        },
        {
          "date": "2026-01-07",
          "value": 5777449.418
        },
        {
          "date": "2026-01-14",
          "value": 5802521.777
        },
        {
          "date": "2026-01-21",
          "value": 5715315.656
        },
        {
          "date": "2026-01-28",
          "value": 5664524.897
        },
        {
          "date": "2026-02-04",
          "value": 5697133.586
        },
        {
          "date": "2026-02-11",
          "value": 5707074.952
        },
        {
          "date": "2026-02-18",
          "value": 5700667.144
        },
        {
          "date": "2026-02-25",
          "value": 5726183.841
        },
        {
          "date": "2026-03-04",
          "value": 5796840.123
        },
        {
          "date": "2026-03-11",
          "value": 5808157.448
        },
        {
          "date": "2026-03-18",
          "value": 5802886.302
        },
        {
          "date": "2026-03-25",
          "value": 5783083.223
        },
        {
          "date": "2026-04-01",
          "value": 5827623.893
        },
        {
          "date": "2026-04-08",
          "value": 5945494.823
        },
        {
          "date": "2026-04-15",
          "value": 5954341.777
        },
        {
          "date": "2026-04-22",
          "value": 5701450.462
        },
        {
          "date": "2026-04-29",
          "value": 5718020.253
        },
        {
          "date": "2026-05-06",
          "value": 5831742.367
        },
        {
          "date": "2026-05-13",
          "value": 5889914.281
        },
        {
          "date": "2026-05-20",
          "value": 5932325.133
        },
        {
          "date": "2026-05-27",
          "value": 5874085.147
        },
        {
          "date": "2026-06-03",
          "value": 5835779.938
        },
        {
          "date": "2026-06-10",
          "value": 5897274.613
        },
        {
          "date": "2026-06-17",
          "value": 5855704.172
        }
      ],
      "is_front_screen": true,
      "note": "CONSTRUCT, not a Fed metric \u2014 context_only (see knobs.net_liquidity)"
    },
    {
      "key": "sofr_iorb",
      "axis": 11,
      "label": "SOFR - IORB",
      "source": "derived:fred_sofr_iorb",
      "value": -0.03,
      "change": 0.01,
      "transform": "level",
      "ewma_z": null,
      "pct_1y": null,
      "pct_3y": null,
      "level_pct_756": 72.486772,
      "robust_z": 1.349,
      "color": "green",
      "staleness": {
        "asof": "2026-06-23",
        "lag_desc": "FRED daily",
        "is_stale": false
      },
      "history": [
        {
          "date": "2026-05-11",
          "value": -0.04999999999999982
        },
        {
          "date": "2026-05-12",
          "value": -0.04999999999999982
        },
        {
          "date": "2026-05-13",
          "value": -0.06000000000000005
        },
        {
          "date": "2026-05-14",
          "value": -0.08999999999999986
        },
        {
          "date": "2026-05-15",
          "value": -0.10000000000000009
        },
        {
          "date": "2026-05-18",
          "value": -0.1200000000000001
        },
        {
          "date": "2026-05-19",
          "value": -0.14000000000000012
        },
        {
          "date": "2026-05-20",
          "value": -0.1499999999999999
        },
        {
          "date": "2026-05-21",
          "value": -0.14000000000000012
        },
        {
          "date": "2026-05-22",
          "value": -0.10000000000000009
        },
        {
          "date": "2026-05-26",
          "value": -0.020000000000000018
        },
        {
          "date": "2026-05-27",
          "value": -0.020000000000000018
        },
        {
          "date": "2026-05-28",
          "value": -0.029999999999999805
        },
        {
          "date": "2026-05-29",
          "value": -0.020000000000000018
        },
        {
          "date": "2026-06-01",
          "value": 0.0
        },
        {
          "date": "2026-06-02",
          "value": -0.020000000000000018
        },
        {
          "date": "2026-06-03",
          "value": -0.040000000000000036
        },
        {
          "date": "2026-06-04",
          "value": -0.029999999999999805
        },
        {
          "date": "2026-06-05",
          "value": -0.020000000000000018
        },
        {
          "date": "2026-06-08",
          "value": -0.020000000000000018
        },
        {
          "date": "2026-06-09",
          "value": -0.04999999999999982
        },
        {
          "date": "2026-06-10",
          "value": -0.06000000000000005
        },
        {
          "date": "2026-06-11",
          "value": -0.04999999999999982
        },
        {
          "date": "2026-06-12",
          "value": 0.0
        },
        {
          "date": "2026-06-15",
          "value": 0.040000000000000036
        },
        {
          "date": "2026-06-16",
          "value": -0.020000000000000018
        },
        {
          "date": "2026-06-17",
          "value": -0.020000000000000018
        },
        {
          "date": "2026-06-18",
          "value": -0.029999999999999805
        },
        {
          "date": "2026-06-22",
          "value": -0.040000000000000036
        },
        {
          "date": "2026-06-23",
          "value": -0.029999999999999805
        }
      ],
      "is_front_screen": true,
      "note": "plumbing flag driver; >25bp = stress"
    },
    {
      "key": "srf_takeup",
      "axis": 11,
      "label": "SRF take-up",
      "source": "nyfed:srf",
      "value": 0.004,
      "change": 0.004,
      "transform": "level",
      "ewma_z": null,
      "pct_1y": null,
      "pct_3y": null,
      "level_pct_756": 70.625,
      "robust_z": 2.0235,
      "color": "green",
      "staleness": {
        "asof": "2026-06-24",
        "lag_desc": "NY Fed daily ops",
        "is_stale": false
      },
      "history": [
        {
          "date": "2026-05-12",
          "value": 0.101
        },
        {
          "date": "2026-05-13",
          "value": 0.004
        },
        {
          "date": "2026-05-14",
          "value": 0.0
        },
        {
          "date": "2026-05-15",
          "value": 0.0
        },
        {
          "date": "2026-05-18",
          "value": 0.001
        },
        {
          "date": "2026-05-19",
          "value": 0.003
        },
        {
          "date": "2026-05-20",
          "value": 0.007
        },
        {
          "date": "2026-05-21",
          "value": 0.003
        },
        {
          "date": "2026-05-22",
          "value": 0.3
        },
        {
          "date": "2026-05-26",
          "value": 0.031
        },
        {
          "date": "2026-05-27",
          "value": 0.11100000000000002
        },
        {
          "date": "2026-05-28",
          "value": 0.001
        },
        {
          "date": "2026-05-29",
          "value": 0.005
        },
        {
          "date": "2026-06-01",
          "value": 0.0
        },
        {
          "date": "2026-06-02",
          "value": 0.012
        },
        {
          "date": "2026-06-03",
          "value": 0.004
        },
        {
          "date": "2026-06-04",
          "value": 0.003
        },
        {
          "date": "2026-06-05",
          "value": 0.004
        },
        {
          "date": "2026-06-08",
          "value": 0.0
        },
        {
          "date": "2026-06-09",
          "value": 0.10300000000000001
        },
        {
          "date": "2026-06-10",
          "value": 0.004
        },
        {
          "date": "2026-06-11",
          "value": 0.001
        },
        {
          "date": "2026-06-12",
          "value": 0.0
        },
        {
          "date": "2026-06-15",
          "value": 0.001
        },
        {
          "date": "2026-06-16",
          "value": 0.021
        },
        {
          "date": "2026-06-17",
          "value": 0.002
        },
        {
          "date": "2026-06-18",
          "value": 0.001
        },
        {
          "date": "2026-06-22",
          "value": 0.0
        },
        {
          "date": "2026-06-23",
          "value": 0.0
        },
        {
          "date": "2026-06-24",
          "value": 0.004
        }
      ],
      "is_front_screen": true,
      "note": "rising off ~0 = stress"
    },
    {
      "key": "btc",
      "axis": 12,
      "label": "BTC",
      "source": "yfinance:BTC-USD",
      "value": 61821.980469,
      "change": 0.013465,
      "transform": "log_return",
      "ewma_z": 0.651852,
      "pct_1y": 54.761905,
      "pct_3y": 56.216931,
      "level_pct_756": 9.656085,
      "robust_z": 0.753616,
      "color": "green",
      "staleness": {
        "asof": "2026-06-25",
        "lag_desc": "EOD delayed",
        "is_stale": false
      },
      "history": [
        {
          "date": "2026-05-27",
          "value": 74344.703125
        },
        {
          "date": "2026-05-28",
          "value": 73536.5546875
        },
        {
          "date": "2026-05-29",
          "value": 73372.5234375
        },
        {
          "date": "2026-05-30",
          "value": 73754.8359375
        },
        {
          "date": "2026-05-31",
          "value": 73579.6875
        },
        {
          "date": "2026-06-01",
          "value": 71319.7734375
        },
        {
          "date": "2026-06-02",
          "value": 66703.65625
        },
        {
          "date": "2026-06-03",
          "value": 64014.3671875
        },
        {
          "date": "2026-06-04",
          "value": 63801.57421875
        },
        {
          "date": "2026-06-05",
          "value": 60922.66796875
        },
        {
          "date": "2026-06-06",
          "value": 60867.4140625
        },
        {
          "date": "2026-06-07",
          "value": 63239.51953125
        },
        {
          "date": "2026-06-08",
          "value": 63090.58984375
        },
        {
          "date": "2026-06-09",
          "value": 61643.78125
        },
        {
          "date": "2026-06-10",
          "value": 61449.2890625
        },
        {
          "date": "2026-06-11",
          "value": 63561.0546875
        },
        {
          "date": "2026-06-12",
          "value": 63543.19921875
        },
        {
          "date": "2026-06-13",
          "value": 64421.32421875
        },
        {
          "date": "2026-06-14",
          "value": 65710.3984375
        },
        {
          "date": "2026-06-15",
          "value": 66289.5
        },
        {
          "date": "2026-06-16",
          "value": 65600.640625
        },
        {
          "date": "2026-06-17",
          "value": 64418.4453125
        },
        {
          "date": "2026-06-18",
          "value": 62896.47265625
        },
        {
          "date": "2026-06-19",
          "value": 63540.8359375
        },
        {
          "date": "2026-06-20",
          "value": 64239.67578125
        },
        {
          "date": "2026-06-21",
          "value": 63237.5390625
        },
        {
          "date": "2026-06-22",
          "value": 63952.10546875
        },
        {
          "date": "2026-06-23",
          "value": 62668.01953125
        },
        {
          "date": "2026-06-24",
          "value": 60995.1328125
        },
        {
          "date": "2026-06-25",
          "value": 61821.98046875
        }
      ],
      "is_front_screen": false,
      "note": null
    },
    {
      "key": "stablecoin_cap",
      "axis": 12,
      "label": "Stablecoin aggregate cap",
      "source": "defillama:stablecoins",
      "value": 312389723421.27,
      "change": -0.001542,
      "transform": "log_return",
      "ewma_z": -1.127478,
      "pct_1y": 77.380952,
      "pct_3y": 77.645503,
      "level_pct_756": 85.846561,
      "robust_z": -0.899074,
      "color": "green",
      "staleness": {
        "asof": "2026-06-25",
        "lag_desc": "DefiLlama daily",
        "is_stale": false
      },
      "history": [
        {
          "date": "2026-05-27",
          "value": 320333727356.0
        },
        {
          "date": "2026-05-28",
          "value": 319717750186.0
        },
        {
          "date": "2026-05-29",
          "value": 318768265582.0
        },
        {
          "date": "2026-05-30",
          "value": 318335352529.0
        },
        {
          "date": "2026-05-31",
          "value": 318100785200.0
        },
        {
          "date": "2026-06-01",
          "value": 317890705207.0
        },
        {
          "date": "2026-06-02",
          "value": 317890714779.0
        },
        {
          "date": "2026-06-03",
          "value": 317205884459.0
        },
        {
          "date": "2026-06-04",
          "value": 316471666936.0
        },
        {
          "date": "2026-06-05",
          "value": 315158958590.0
        },
        {
          "date": "2026-06-06",
          "value": 314591010637.0
        },
        {
          "date": "2026-06-07",
          "value": 314119695877.0
        },
        {
          "date": "2026-06-08",
          "value": 314246651239.0
        },
        {
          "date": "2026-06-09",
          "value": 314703065413.0
        },
        {
          "date": "2026-06-10",
          "value": 313726013359.0
        },
        {
          "date": "2026-06-11",
          "value": 313632906460.0
        },
        {
          "date": "2026-06-12",
          "value": 313489024645.0
        },
        {
          "date": "2026-06-13",
          "value": 313194615283.0
        },
        {
          "date": "2026-06-14",
          "value": 313253163286.0
        },
        {
          "date": "2026-06-15",
          "value": 313155354284.0
        },
        {
          "date": "2026-06-16",
          "value": 313606632803.0
        },
        {
          "date": "2026-06-17",
          "value": 313484896767.0
        },
        {
          "date": "2026-06-18",
          "value": 313139082334.0
        },
        {
          "date": "2026-06-19",
          "value": 313314425047.0
        },
        {
          "date": "2026-06-20",
          "value": 313342947578.0
        },
        {
          "date": "2026-06-21",
          "value": 313401867156.0
        },
        {
          "date": "2026-06-22",
          "value": 313444117954.0
        },
        {
          "date": "2026-06-23",
          "value": 313504750569.0
        },
        {
          "date": "2026-06-24",
          "value": 312871825162.0
        },
        {
          "date": "2026-06-25",
          "value": 312389723421.27
        }
      ],
      "is_front_screen": false,
      "note": "crypto dry powder; keep small"
    }
  ],
  "cards": [
    {
      "title": "Fed Broad USD (DTWEXBGS) anomaly",
      "metric": "Fed Broad USD (DTWEXBGS) +0.84% (fred:DTWEXBGS)",
      "score_desc": "99th pct / +3.4-sigma; level 35th pct of 3y",
      "why_now": {
        "percentile_or_z": "99th pct / +3.4-sigma",
        "calendar_event": null,
        "cross_asset_confirm_or_contradict": "confirmed by HY OAS (BAMLH0A0HYM2)"
      },
      "color": "red",
      "is_banner": false,
      "tile_keys": [
        "usd_broad"
      ]
    }
  ],
  "calendar": [],
  "plumbing_flags": [
    {
      "name": "srf_takeup",
      "value": 0.004,
      "triggered": true,
      "note": "SRF take-up 0.0bn off zero = funding stress",
      "staleness": {
        "asof": "2026-06-24",
        "lag_desc": "NY Fed daily ops",
        "is_stale": false
      }
    },
    {
      "name": "sofr_minus_iorb",
      "value": -0.029999999999999805,
      "triggered": false,
      "note": "SOFR-IORB -3bp > 25bp threshold = repo stress",
      "staleness": {
        "asof": "2026-06-23",
        "lag_desc": "FRED daily",
        "is_stale": false
      }
    },
    {
      "name": "net_liq_5d_drop",
      "value": -34210.10900000017,
      "triggered": true,
      "note": "Net liquidity 5d change -34210 \u2014 CONTEXT only, not an oracle (knobs.net_liquidity=context_only)",
      "staleness": {
        "asof": "2026-06-17",
        "lag_desc": "H.4.1 weekly Thu",
        "is_stale": false
      }
    }
  ],
  "corr_breaks": [
    {
      "name": "gold_vs_realyield_usd",
      "residual_z": 1.3798,
      "persistence_days": 0,
      "triggered": false,
      "sign_flip": false,
      "note": "residual +1.38 EWMA-sigma, persisted 0d (need 3d)"
    },
    {
      "name": "hy_oas_vs_acwi_vix",
      "residual_z": 1.5979,
      "persistence_days": 0,
      "triggered": false,
      "sign_flip": false,
      "note": "residual +1.60 EWMA-sigma, persisted 0d (need 3d)"
    },
    {
      "name": "stock_bond_corr",
      "residual_z": 0.6979,
      "persistence_days": 0,
      "triggered": false,
      "sign_flip": false,
      "note": "residual +0.70 EWMA-sigma, persisted 0d (need 3d)"
    }
  ],
  "dog_didnt_bark": []
}
